tests/__init__.py
tests/test_yabai_layout_details.py
tests/test_yabai_navigator.py
tests/test_yabai_stacked_window_provider.py
yabai_stack_navigator/__init__.py
yabai_stack_navigator/__main__.py
yabai_stack_navigator/cli.py
yabai_stack_navigator/yabai_layout_details.py
yabai_stack_navigator/yabai_navigator.py
yabai_stack_navigator/yabai_provider.py
yabai_stack_navigator/yabai_stacked_window_provider.py
yabai_stack_navigator-1.0.8.dist-info/LICENSE
yabai_stack_navigator-1.0.8.dist-info/METADATA
yabai_stack_navigator-1.0.8.dist-info/WHEEL
yabai_stack_navigator-1.0.8.dist-info/entry_points.txt
yabai_stack_navigator-1.0.8.dist-info/top_level.txt
yabai_stack_navigator-1.0.8.dist-info/RECORD
