Metadata-Version: 2.1
Name: yabai-stack-navigator
Version: 1.0.8
Summary: Script to make navigating between stacks on Yabai easier.
Author: Sendhil Panchadsaram
License: MIT
Project-URL: GitHub, https://github.com/sendhil/yabai-stack-navigator
License-File: LICENSE
